lfg/__init__.py
litecfg-0.0.0.dist-info/LICENSE
litecfg-0.0.0.dist-info/METADATA
litecfg-0.0.0.dist-info/WHEEL
litecfg-0.0.0.dist-info/top_level.txt
litecfg-0.0.0.dist-info/RECORD
