Metadata-Version: 2.1
Name: litecfg
Version: 0.0.0
Summary: Convert lcfg to Python object
Home-page: https://github.com/Cure-Dev/pylcfg
Author: Cure-X
Author-email: admin@cure-x.net
License-File: LICENSE
